{"coefs": {"mana_cost_jaccard": 0.0, "cmc_similarity": 0.0, "type_line_jaccard": 0.0, "oracle_text_BERT": 0.0, "color_identity_jaccard": 1.0, "keywords_jaccard": 0.5, "power_similarity": 0.0, "toughness_similarity": 0.0}, "conjunto": ["Abrade", "Beamtown Beatstick", "Knife", "Sunfire Torch", "Barbed Batterfist", "Hexgold Halberd", "Vulshok Splitter", "Dragonwing Glider", "Ramosian Greatsword", "Dire Flail // Dire Blunderbuss", "Idol of the Deep King // Sovereign's Macuahuitl", "Urabrask // The Great Work", "Dowsing Device // Geode Grotto", "Furnace Gremlin", "Searing Barb", "Marauding Dreadship", "Reckless Lackey", "Bonehoard Dracosaur", "Enterprising Scallywag", "Flick a Coin", "Furnace Reins", "Plundering Pirate", "Korvold and the Noble Thief", "Season of the Bold", "Hell to Pay", "Great Train Heist", "Blooming Blast", "Mine Raider", "Grabby Giant // That's Mine", "Hit the Mother Lode", "Charming Scoundrel", "Rampaging Raptor", "Skitterbeam Battalion", "Sawblade Scamp", "Red Herring", "Hotfoot Gnome", "Kolaghan Warmonger", "Stormsplitter", "Frantic Scapegoat", "Monastery Swiftspear", "Cunning Coyote", "Resilient Roadrunner", "Furnace Host Charger", "Exuberant Fuseling", "Belligerent Yearling", "Electrostatic Infantry", "Thrashing Frontliner", "Child of the Volcano", "Molten Monstrosity", "Trumpeting Carnosaur", "Hellspur Brute", "Stingerback Terror", "Seismic Monstrosaur", "Geological Appraiser", "Daring Discovery", "Longhorn Sharpshooter", "Brimstone Roundup", "Highway Robbery", "Irascible Wolverine", "Demonic Ruckus", "Deadeye Duelist"]}